pypdf_cli.py
pypdf_cli-1.0.0.dist-info/entry_points.txt
pypdf_cli-1.0.0.dist-info/LICENSE
pypdf_cli-1.0.0.dist-info/WHEEL
pypdf_cli-1.0.0.dist-info/METADATA
pypdf_cli-1.0.0.dist-info/RECORD
