Metadata-Version: 2.1
Name: pypdf-cli
Version: 1.0.0
Summary: A Python-based CLI that allows for comfortable every-day PDF manipulation with pypdf.
Keywords: pdf,cli,pypdf,click
Author-email: Tobias Lass <tobi208@github.com>
Requires-Python: >=3.6
Classifier: Programming Language :: Python :: 3
Classifier: License :: OSI Approved :: GNU General Public License v3 (GPLv3)
Classifier: Operating System :: OS Independent
Requires-Dist: click>=8.0.3
Requires-Dist: pypdf>=3.0.0
Requires-Dist: pytest>=7.0.0 ; extra == "test"
Project-URL: Bug Tracker, https://github.com/tobi208/pypdf-cli/issues
Project-URL: Homepage, https://github.com/tobi208/pypdf-cli
Provides-Extra: test
